sqt/__init__.py
sqtui/__init__.py
sqtui-0.0.5.dist-info/LICENSE
sqtui-0.0.5.dist-info/METADATA
sqtui-0.0.5.dist-info/WHEEL
sqtui-0.0.5.dist-info/top_level.txt
sqtui-0.0.5.dist-info/RECORD
