Metadata-Version: 2.1
Name: sqtui
Version: 0.0.5
Summary: Safe QT, a QT wrapper for automatic selection of python QT libs (PyQt, PySide)
Home-page: https://github.com/ParisNeo/SQTUI
Author: Saifeddine ALOUI
Author-email: aloui.saifeddine@gmail.com
License: UNKNOWN
Platform: UNKNOWN
Classifier: Programming Language :: Python :: 3
Classifier: License :: OSI Approved :: MIT License
Classifier: Operating System :: OS Independent
